wordcab/__init__.py
wordcab/__main__.py
wordcab/api.py
wordcab/client.py
wordcab/config.py
wordcab/live.py
wordcab/login.py
wordcab/py.typed
wordcab/utils.py
wordcab/core_objects/__init__.py
wordcab/core_objects/job.py
wordcab/core_objects/source.py
wordcab/core_objects/stats.py
wordcab/core_objects/summary.py
wordcab/core_objects/transcript.py
wordcab/core_objects/utils.py
wordcab-0.7.2.dist-info/METADATA
wordcab-0.7.2.dist-info/WHEEL
wordcab-0.7.2.dist-info/entry_points.txt
wordcab-0.7.2.dist-info/licenses/LICENSE
wordcab-0.7.2.dist-info/RECORD
